{
  "obsidian-california-coast-theme@@strong-color@@light": "#D03636",
  "minimal-style@@checkbox-shape": "checkbox-square",
  "blue-topaz-theme@@fix-right-ribbon": false,
  "blue-topaz-theme@@hide-left-ribbon": false,
  "blue-topaz-theme@@layout-style-options": "layout-style-options-default",
  "blue-topaz-theme@@hide-titlebar-text": true,
  "blue-topaz-theme@@bt-status-off": true,
  "blue-topaz-theme@@translucent-setting-panel": false,
  "blue-topaz-theme@@fancy-hr": "fancy-hr-no-icon",
  "blue-topaz-theme@@file-name-animation": true,
  "blue-topaz-theme@@blockquote-style-change-options": "blockquote-style-outline",
  "blue-topaz-theme@@style-options-for-kanban-plugin-dynamic": "style-options-for-kanban-plugin-dynamic-neon-two",
  "blue-topaz-theme@@style-options-for-kanban-plugin-static": "style-options-for-kanban-plugin-static-little-color",
  "blue-topaz-theme@@h1-text-align-settings": "h1-text-align-center",
  "things-style@@text": "'LXGW WenKai Screen R',-apple-system,BlinkMacSystemFont,\"Segoe UI\",Roboto,Oxygen-Sans,Ubuntu,Cantarell,\"Helvetica Neue\",sans-serif",
  "things-style@@text-editor": "'LXGW WenKai Screen R',-apple-system,BlinkMacSystemFont,\"Segoe UI\",Roboto,Oxygen-Sans,Ubuntu,Cantarell,\"Helvetica Neue\",sans-serif",
  "things-style@@font-monospace": "'LXGW WenKai Screen R',JetBrains Mono,Menlo,SFMono-Regular,Consolas,\"Roboto Mono\",monospace",
  "things-style@@font-ui": "'LXGW WenKai Screen R',-apple-system,BlinkMacSystemFont,\"Segoe UI\",Roboto,Oxygen-Sans,Ubuntu,Cantarell,\"Helvetica Neue\",sans-serif",
  "things-style@@minimal-icons-off": false,
  "things-style@@full-file-names": true,
  "things-style@@macOS-translucent": true,
  "things-style@@cursor": "default",
  "things-style@@floating-button-off": false,
  "blue-topaz-theme@@whole-code-wrap": true,
  "blue-topaz-theme@@text-indentation-two-em": true,
  "blue-topaz-theme@@list-style-change-options": "list-vertical-line-two",
  "blue-topaz-theme@@list-style-change-options-edit": "list-no-line-in-edit",
  "blue-topaz-theme@@rainbow-ordered-list": false,
  "blue-topaz-theme@@rainbow-checkbox": false,
  "blue-topaz-theme@@light-background-color-files": true,
  "blue-topaz-theme@@unmuted-collapsed-folder": false,
  "blue-topaz-theme@@remove-file-icons": true,
  "blue-topaz-theme@@folder-icons": true,
  "blue-topaz-theme@@folder-style-change-options-colorful": true,
  "blue-topaz-theme@@folder-style-change-options-colorful-subfolder": "folder-colorful-four",
  "blue-topaz-theme@@font-family-change-to-default": false,
  "blue-topaz-theme@@show-border-table": true,
  "blue-topaz-theme@@table-style-options": "table-style-two",
  "blue-topaz-theme@@no-wrapped-table": false,
  "blue-topaz-theme@@font-size-vault-name": "0.4em"
}